<chunk name="Object" index="0">
  <items count="2">
    <item name="GUID" type_name="gh_guid" type_code="9">3cadddef-1e2b-4c09-9390-0e8f78f7609f</item>
    <item name="Name" type_name="gh_string" type_code="10">Merge</item>
  </items>
  <chunks count="1">
    <chunk name="Container">
      <items count="5">
        <item name="Description" type_name="gh_string" type_code="10">Merge a bunch of data streams</item>
        <item name="Hidden" type_name="gh_bool" type_code="1">true</item>
        <item name="InstanceGuid" type_name="gh_guid" type_code="9">d69ca8ff-21a8-416b-b6f6-08e38798f6d4</item>
        <item name="Name" type_name="gh_string" type_code="10">Merge</item>
        <item name="NickName" type_name="gh_string" type_code="10">Merge</item>
      </items>
      <chunks count="2">
        <chunk name="Attributes">
          <items count="2">
            <item name="Bounds" type_name="gh_drawing_rectanglef" type_code="35">
              <X>9163</X>
              <Y>-3425</Y>
              <W>88</W>
              <H>64</H>
            </item>
            <item name="Pivot" type_name="gh_drawing_pointf" type_code="31">
              <X>9217</X>
              <Y>-3393</Y>
            </item>
          </items>
        </chunk>
        <chunk name="ParameterData">
          <items count="6">
            <item name="InputCount" type_name="gh_int32" type_code="3">3</item>
            <item name="InputId" index="0" type_name="gh_guid" type_code="9">8ec86459-bf01-4409-baee-174d0d2b13d0</item>
            <item name="InputId" index="1" type_name="gh_guid" type_code="9">8ec86459-bf01-4409-baee-174d0d2b13d0</item>
            <item name="InputId" index="2" type_name="gh_guid" type_code="9">8ec86459-bf01-4409-baee-174d0d2b13d0</item>
            <item name="OutputCount" type_name="gh_int32" type_code="3">1</item>
            <item name="OutputId" index="0" type_name="gh_guid" type_code="9">8ec86459-bf01-4409-baee-174d0d2b13d0</item>
          </items>
          <chunks count="4">
            <chunk name="InputParam" index="0">
              <items count="9">
                <item name="Access" type_name="gh_int32" type_code="3">2</item>
                <item name="Description" type_name="gh_string" type_code="10">Data stream 1</item>
                <item name="InstanceGuid" type_name="gh_guid" type_code="9">55481895-511e-4b73-bf59-0fef7dbc36dc</item>
                <item name="Mapping" type_name="gh_int32" type_code="3">1</item>
                <item name="Mutable" type_name="gh_bool" type_code="1">false</item>
                <item name="Name" type_name="gh_string" type_code="10">Data 1</item>
                <item name="NickName" type_name="gh_string" type_code="10">D1</item>
                <item name="Optional" type_name="gh_bool" type_code="1">true</item>
                <item name="SourceCount" type_name="gh_int32" type_code="3">0</item>
              </items>
              <chunks count="1">
                <chunk name="Attributes">
                  <items count="2">
                    <item name="Bounds" type_name="gh_drawing_rectanglef" type_code="35">
                      <X>9165</X>
                      <Y>-3423</Y>
                      <W>37</W>
                      <H>20</H>
                    </item>
                    <item name="Pivot" type_name="gh_drawing_pointf" type_code="31">
                      <X>9193</X>
                      <Y>-3413</Y>
                    </item>
                  </items>
                </chunk>
              </chunks>
            </chunk>
            <chunk name="InputParam" index="1">
              <items count="10">
                <item name="Access" type_name="gh_int32" type_code="3">2</item>
                <item name="Description" type_name="gh_string" type_code="10">Data stream 2</item>
                <item name="InstanceGuid" type_name="gh_guid" type_code="9">a3181573-8a6c-491c-9f24-8f17726ebfa3</item>
                <item name="Mapping" type_name="gh_int32" type_code="3">1</item>
                <item name="Mutable" type_name="gh_bool" type_code="1">false</item>
                <item name="Name" type_name="gh_string" type_code="10">Data 2</item>
                <item name="NickName" type_name="gh_string" type_code="10">D2</item>
                <item name="Optional" type_name="gh_bool" type_code="1">true</item>
                <item name="Source" index="0" type_name="gh_guid" type_code="9">0ce8bc02-2c85-47ee-8687-fa08f03a4dc2</item>
                <item name="SourceCount" type_name="gh_int32" type_code="3">1</item>
              </items>
              <chunks count="1">
                <chunk name="Attributes">
                  <items count="2">
                    <item name="Bounds" type_name="gh_drawing_rectanglef" type_code="35">
                      <X>9165</X>
                      <Y>-3403</Y>
                      <W>37</W>
                      <H>20</H>
                    </item>
                    <item name="Pivot" type_name="gh_drawing_pointf" type_code="31">
                      <X>9193</X>
                      <Y>-3393</Y>
                    </item>
                  </items>
                </chunk>
              </chunks>
            </chunk>
            <chunk name="InputParam" index="2">
              <items count="8">
                <item name="Access" type_name="gh_int32" type_code="3">2</item>
                <item name="Description" type_name="gh_string" type_code="10">Data stream 3</item>
                <item name="InstanceGuid" type_name="gh_guid" type_code="9">bd423641-b219-48d1-9743-d9205d5a99fe</item>
                <item name="Mutable" type_name="gh_bool" type_code="1">false</item>
                <item name="Name" type_name="gh_string" type_code="10">Data 3</item>
                <item name="NickName" type_name="gh_string" type_code="10">D3</item>
                <item name="Optional" type_name="gh_bool" type_code="1">true</item>
                <item name="SourceCount" type_name="gh_int32" type_code="3">0</item>
              </items>
              <chunks count="1">
                <chunk name="Attributes">
                  <items count="2">
                    <item name="Bounds" type_name="gh_drawing_rectanglef" type_code="35">
                      <X>9165</X>
                      <Y>-3383</Y>
                      <W>37</W>
                      <H>20</H>
                    </item>
                    <item name="Pivot" type_name="gh_drawing_pointf" type_code="31">
                      <X>9193</X>
                      <Y>-3373</Y>
                    </item>
                  </items>
                </chunk>
              </chunks>
            </chunk>
            <chunk name="OutputParam" index="0">
              <items count="7">
                <item name="Access" type_name="gh_int32" type_code="3">2</item>
                <item name="Description" type_name="gh_string" type_code="10">Result of merge</item>
                <item name="InstanceGuid" type_name="gh_guid" type_code="9">82239d1d-abd3-4f10-b0e8-739e6e0e94fb</item>
                <item name="Name" type_name="gh_string" type_code="10">Result</item>
                <item name="NickName" type_name="gh_string" type_code="10">R</item>
                <item name="Optional" type_name="gh_bool" type_code="1">false</item>
                <item name="SourceCount" type_name="gh_int32" type_code="3">0</item>
              </items>
              <chunks count="1">
                <chunk name="Attributes">
                  <items count="2">
                    <item name="Bounds" type_name="gh_drawing_rectanglef" type_code="35">
                      <X>9232</X>
                      <Y>-3423</Y>
                      <W>17</W>
                      <H>60</H>
                    </item>
                    <item name="Pivot" type_name="gh_drawing_pointf" type_code="31">
                      <X>9240.5</X>
                      <Y>-3393</Y>
                    </item>
                  </items>
                </chunk>
              </chunks>
            </chunk>
          </chunks>
        </chunk>
      </chunks>
    </chunk>
  </chunks>
</chunk>