<chunk name="Object" index="0">
  <items count="3">
    <item name="GUID" type_name="gh_guid" type_code="9">2e389289-4ccb-4f4a-9ee3-71dc7f62ee25</item>
    <item name="Lib" type_name="gh_guid" type_code="9">713fc0cc-8d34-4024-96f8-1a1edc8e378a</item>
    <item name="Name" type_name="gh_string" type_code="10">AXIS Movement - KUKA|prc</item>
  </items>
  <chunks count="1">
    <chunk name="Container">
      <items count="6">
        <item name="Description" type_name="gh_string" type_code="10">Robot movement defined through axis values. The robot will move to the given axis position in the most efficient manner.</item>
        <item name="InstanceGuid" type_name="gh_guid" type_code="9">e6354206-162a-4c4c-a9a9-72b44c73acf9</item>
        <item name="Name" type_name="gh_string" type_code="10">AXIS Movement - KUKA|prc</item>
        <item name="NickName" type_name="gh_string" type_code="10">AXIS MOVE</item>
        <item name="extaxenabled" type_name="gh_bool" type_code="1">false</item>
        <item name="interpolation" type_name="gh_string" type_code="10">C_PTP</item>
      </items>
      <chunks count="2">
        <chunk name="Attributes">
          <items count="2">
            <item name="Bounds" type_name="gh_drawing_rectanglef" type_code="35">
              <X>28327</X>
              <Y>4814</Y>
              <W>128</W>
              <H>144</H>
            </item>
            <item name="Pivot" type_name="gh_drawing_pointf" type_code="31">
              <X>28370</X>
              <Y>4886</Y>
            </item>
          </items>
        </chunk>
        <chunk name="ParameterData">
          <items count="10">
            <item name="InputCount" type_name="gh_int32" type_code="3">7</item>
            <item name="InputId" index="0" type_name="gh_guid" type_code="9">3e8ca6be-fda8-4aaf-b5c0-3c54c8bb7312</item>
            <item name="InputId" index="1" type_name="gh_guid" type_code="9">3e8ca6be-fda8-4aaf-b5c0-3c54c8bb7312</item>
            <item name="InputId" index="2" type_name="gh_guid" type_code="9">3e8ca6be-fda8-4aaf-b5c0-3c54c8bb7312</item>
            <item name="InputId" index="3" type_name="gh_guid" type_code="9">3e8ca6be-fda8-4aaf-b5c0-3c54c8bb7312</item>
            <item name="InputId" index="4" type_name="gh_guid" type_code="9">3e8ca6be-fda8-4aaf-b5c0-3c54c8bb7312</item>
            <item name="InputId" index="5" type_name="gh_guid" type_code="9">3e8ca6be-fda8-4aaf-b5c0-3c54c8bb7312</item>
            <item name="InputId" index="6" type_name="gh_guid" type_code="9">2e3ab970-8545-46bb-836c-1c11e5610bce</item>
            <item name="OutputCount" type_name="gh_int32" type_code="3">1</item>
            <item name="OutputId" index="0" type_name="gh_guid" type_code="9">9fe6fd0d-de26-473a-bb30-5ec95cb4775a</item>
          </items>
          <chunks count="8">
            <chunk name="InputParam" index="0">
              <items count="8">
                <item name="Description" type_name="gh_string" type_code="10">Axis 1 value in degrees</item>
                <item name="InstanceGuid" type_name="gh_guid" type_code="9">67e531e3-4cd8-41ba-9ad0-cc8caee2334d</item>
                <item name="Mutable" type_name="gh_bool" type_code="1">false</item>
                <item name="Name" type_name="gh_string" type_code="10">Axis 1</item>
                <item name="NickName" type_name="gh_string" type_code="10">A01</item>
                <item name="Optional" type_name="gh_bool" type_code="1">false</item>
                <item name="Source" index="0" type_name="gh_guid" type_code="9">eb3a06c0-79f3-473f-9fe4-707ab6092c93</item>
                <item name="SourceCount" type_name="gh_int32" type_code="3">1</item>
              </items>
              <chunks count="2">
                <chunk name="Attributes">
                  <items count="2">
                    <item name="Bounds" type_name="gh_drawing_rectanglef" type_code="35">
                      <X>28329</X>
                      <Y>4816</Y>
                      <W>26</W>
                      <H>20</H>
                    </item>
                    <item name="Pivot" type_name="gh_drawing_pointf" type_code="31">
                      <X>28343.5</X>
                      <Y>4826</Y>
                    </item>
                  </items>
                </chunk>
                <chunk name="PersistentData">
                  <items count="1">
                    <item name="Count" type_name="gh_int32" type_code="3">1</item>
                  </items>
                  <chunks count="1">
                    <chunk name="Branch" index="0">
                      <items count="2">
                        <item name="Count" type_name="gh_int32" type_code="3">1</item>
                        <item name="Path" type_name="gh_string" type_code="10">{0}</item>
                      </items>
                      <chunks count="1">
                        <chunk name="Item" index="0">
                          <items count="1">
                            <item name="number" type_name="gh_double" type_code="6">0</item>
                          </items>
                        </chunk>
                      </chunks>
                    </chunk>
                  </chunks>
                </chunk>
              </chunks>
            </chunk>
            <chunk name="InputParam" index="1">
              <items count="8">
                <item name="Description" type_name="gh_string" type_code="10">Axis 2 value in degrees</item>
                <item name="InstanceGuid" type_name="gh_guid" type_code="9">1a4836c8-1c7c-48fc-9cd2-10f97efdd59a</item>
                <item name="Mutable" type_name="gh_bool" type_code="1">false</item>
                <item name="Name" type_name="gh_string" type_code="10">Axis 2</item>
                <item name="NickName" type_name="gh_string" type_code="10">A02</item>
                <item name="Optional" type_name="gh_bool" type_code="1">false</item>
                <item name="Source" index="0" type_name="gh_guid" type_code="9">910c7b5b-6c33-4e37-8456-c2511dc30b25</item>
                <item name="SourceCount" type_name="gh_int32" type_code="3">1</item>
              </items>
              <chunks count="2">
                <chunk name="Attributes">
                  <items count="2">
                    <item name="Bounds" type_name="gh_drawing_rectanglef" type_code="35">
                      <X>28329</X>
                      <Y>4836</Y>
                      <W>26</W>
                      <H>20</H>
                    </item>
                    <item name="Pivot" type_name="gh_drawing_pointf" type_code="31">
                      <X>28343.5</X>
                      <Y>4846</Y>
                    </item>
                  </items>
                </chunk>
                <chunk name="PersistentData">
                  <items count="1">
                    <item name="Count" type_name="gh_int32" type_code="3">1</item>
                  </items>
                  <chunks count="1">
                    <chunk name="Branch" index="0">
                      <items count="2">
                        <item name="Count" type_name="gh_int32" type_code="3">1</item>
                        <item name="Path" type_name="gh_string" type_code="10">{0}</item>
                      </items>
                      <chunks count="1">
                        <chunk name="Item" index="0">
                          <items count="1">
                            <item name="number" type_name="gh_double" type_code="6">-90</item>
                          </items>
                        </chunk>
                      </chunks>
                    </chunk>
                  </chunks>
                </chunk>
              </chunks>
            </chunk>
            <chunk name="InputParam" index="2">
              <items count="8">
                <item name="Description" type_name="gh_string" type_code="10">Axis 3 value in degrees</item>
                <item name="InstanceGuid" type_name="gh_guid" type_code="9">8e8f1809-117d-4cdf-b9a2-e73938700905</item>
                <item name="Mutable" type_name="gh_bool" type_code="1">false</item>
                <item name="Name" type_name="gh_string" type_code="10">Axis 3</item>
                <item name="NickName" type_name="gh_string" type_code="10">A03</item>
                <item name="Optional" type_name="gh_bool" type_code="1">false</item>
                <item name="Source" index="0" type_name="gh_guid" type_code="9">b48044f8-f3c3-4db7-a9f7-8a549f3570e8</item>
                <item name="SourceCount" type_name="gh_int32" type_code="3">1</item>
              </items>
              <chunks count="2">
                <chunk name="Attributes">
                  <items count="2">
                    <item name="Bounds" type_name="gh_drawing_rectanglef" type_code="35">
                      <X>28329</X>
                      <Y>4856</Y>
                      <W>26</W>
                      <H>20</H>
                    </item>
                    <item name="Pivot" type_name="gh_drawing_pointf" type_code="31">
                      <X>28343.5</X>
                      <Y>4866</Y>
                    </item>
                  </items>
                </chunk>
                <chunk name="PersistentData">
                  <items count="1">
                    <item name="Count" type_name="gh_int32" type_code="3">1</item>
                  </items>
                  <chunks count="1">
                    <chunk name="Branch" index="0">
                      <items count="2">
                        <item name="Count" type_name="gh_int32" type_code="3">1</item>
                        <item name="Path" type_name="gh_string" type_code="10">{0}</item>
                      </items>
                      <chunks count="1">
                        <chunk name="Item" index="0">
                          <items count="1">
                            <item name="number" type_name="gh_double" type_code="6">90</item>
                          </items>
                        </chunk>
                      </chunks>
                    </chunk>
                  </chunks>
                </chunk>
              </chunks>
            </chunk>
            <chunk name="InputParam" index="3">
              <items count="8">
                <item name="Description" type_name="gh_string" type_code="10">Axis 4 value in degrees</item>
                <item name="InstanceGuid" type_name="gh_guid" type_code="9">256b0fa9-6136-44fa-bf59-3e214cd71a95</item>
                <item name="Mutable" type_name="gh_bool" type_code="1">false</item>
                <item name="Name" type_name="gh_string" type_code="10">Axis 4</item>
                <item name="NickName" type_name="gh_string" type_code="10">A04</item>
                <item name="Optional" type_name="gh_bool" type_code="1">false</item>
                <item name="Source" index="0" type_name="gh_guid" type_code="9">2d04b4f6-6529-4ee2-84be-9167cfd0fe53</item>
                <item name="SourceCount" type_name="gh_int32" type_code="3">1</item>
              </items>
              <chunks count="2">
                <chunk name="Attributes">
                  <items count="2">
                    <item name="Bounds" type_name="gh_drawing_rectanglef" type_code="35">
                      <X>28329</X>
                      <Y>4876</Y>
                      <W>26</W>
                      <H>20</H>
                    </item>
                    <item name="Pivot" type_name="gh_drawing_pointf" type_code="31">
                      <X>28343.5</X>
                      <Y>4886</Y>
                    </item>
                  </items>
                </chunk>
                <chunk name="PersistentData">
                  <items count="1">
                    <item name="Count" type_name="gh_int32" type_code="3">1</item>
                  </items>
                  <chunks count="1">
                    <chunk name="Branch" index="0">
                      <items count="2">
                        <item name="Count" type_name="gh_int32" type_code="3">1</item>
                        <item name="Path" type_name="gh_string" type_code="10">{0}</item>
                      </items>
                      <chunks count="1">
                        <chunk name="Item" index="0">
                          <items count="1">
                            <item name="number" type_name="gh_double" type_code="6">0</item>
                          </items>
                        </chunk>
                      </chunks>
                    </chunk>
                  </chunks>
                </chunk>
              </chunks>
            </chunk>
            <chunk name="InputParam" index="4">
              <items count="8">
                <item name="Description" type_name="gh_string" type_code="10">Axis 5 value in degrees</item>
                <item name="InstanceGuid" type_name="gh_guid" type_code="9">455fb9ca-5002-44e5-b396-6d28b74ed739</item>
                <item name="Mutable" type_name="gh_bool" type_code="1">false</item>
                <item name="Name" type_name="gh_string" type_code="10">Axis 5</item>
                <item name="NickName" type_name="gh_string" type_code="10">A05</item>
                <item name="Optional" type_name="gh_bool" type_code="1">false</item>
                <item name="Source" index="0" type_name="gh_guid" type_code="9">bfa67d02-6c51-4205-a331-01ecd00cf5fb</item>
                <item name="SourceCount" type_name="gh_int32" type_code="3">1</item>
              </items>
              <chunks count="2">
                <chunk name="Attributes">
                  <items count="2">
                    <item name="Bounds" type_name="gh_drawing_rectanglef" type_code="35">
                      <X>28329</X>
                      <Y>4896</Y>
                      <W>26</W>
                      <H>20</H>
                    </item>
                    <item name="Pivot" type_name="gh_drawing_pointf" type_code="31">
                      <X>28343.5</X>
                      <Y>4906</Y>
                    </item>
                  </items>
                </chunk>
                <chunk name="PersistentData">
                  <items count="1">
                    <item name="Count" type_name="gh_int32" type_code="3">1</item>
                  </items>
                  <chunks count="1">
                    <chunk name="Branch" index="0">
                      <items count="2">
                        <item name="Count" type_name="gh_int32" type_code="3">1</item>
                        <item name="Path" type_name="gh_string" type_code="10">{0}</item>
                      </items>
                      <chunks count="1">
                        <chunk name="Item" index="0">
                          <items count="1">
                            <item name="number" type_name="gh_double" type_code="6">0</item>
                          </items>
                        </chunk>
                      </chunks>
                    </chunk>
                  </chunks>
                </chunk>
              </chunks>
            </chunk>
            <chunk name="InputParam" index="5">
              <items count="8">
                <item name="Description" type_name="gh_string" type_code="10">Axis 6 value in degrees</item>
                <item name="InstanceGuid" type_name="gh_guid" type_code="9">87b31cc4-aaca-42f5-9a25-27d2dc786fd4</item>
                <item name="Mutable" type_name="gh_bool" type_code="1">false</item>
                <item name="Name" type_name="gh_string" type_code="10">Axis 6</item>
                <item name="NickName" type_name="gh_string" type_code="10">A06</item>
                <item name="Optional" type_name="gh_bool" type_code="1">false</item>
                <item name="Source" index="0" type_name="gh_guid" type_code="9">b630c1bc-07b5-4b41-a2b4-1368444525a3</item>
                <item name="SourceCount" type_name="gh_int32" type_code="3">1</item>
              </items>
              <chunks count="2">
                <chunk name="Attributes">
                  <items count="2">
                    <item name="Bounds" type_name="gh_drawing_rectanglef" type_code="35">
                      <X>28329</X>
                      <Y>4916</Y>
                      <W>26</W>
                      <H>20</H>
                    </item>
                    <item name="Pivot" type_name="gh_drawing_pointf" type_code="31">
                      <X>28343.5</X>
                      <Y>4926</Y>
                    </item>
                  </items>
                </chunk>
                <chunk name="PersistentData">
                  <items count="1">
                    <item name="Count" type_name="gh_int32" type_code="3">1</item>
                  </items>
                  <chunks count="1">
                    <chunk name="Branch" index="0">
                      <items count="2">
                        <item name="Count" type_name="gh_int32" type_code="3">1</item>
                        <item name="Path" type_name="gh_string" type_code="10">{0}</item>
                      </items>
                      <chunks count="1">
                        <chunk name="Item" index="0">
                          <items count="1">
                            <item name="number" type_name="gh_double" type_code="6">0</item>
                          </items>
                        </chunk>
                      </chunks>
                    </chunk>
                  </chunks>
                </chunk>
              </chunks>
            </chunk>
            <chunk name="InputParam" index="6">
              <items count="7">
                <item name="Description" type_name="gh_string" type_code="10">Robot speed defined in percent</item>
                <item name="InstanceGuid" type_name="gh_guid" type_code="9">214a268b-ea87-43f2-9aea-2fd7ba05a8cf</item>
                <item name="Mutable" type_name="gh_bool" type_code="1">false</item>
                <item name="Name" type_name="gh_string" type_code="10">Speed</item>
                <item name="NickName" type_name="gh_string" type_code="10">VEL</item>
                <item name="Optional" type_name="gh_bool" type_code="1">true</item>
                <item name="SourceCount" type_name="gh_int32" type_code="3">0</item>
              </items>
              <chunks count="1">
                <chunk name="Attributes">
                  <items count="2">
                    <item name="Bounds" type_name="gh_drawing_rectanglef" type_code="35">
                      <X>28329</X>
                      <Y>4936</Y>
                      <W>26</W>
                      <H>20</H>
                    </item>
                    <item name="Pivot" type_name="gh_drawing_pointf" type_code="31">
                      <X>28343.5</X>
                      <Y>4946</Y>
                    </item>
                  </items>
                </chunk>
              </chunks>
            </chunk>
            <chunk name="OutputParam" index="0">
              <items count="7">
                <item name="Access" type_name="gh_int32" type_code="3">1</item>
                <item name="Description" type_name="gh_string" type_code="10">KUKA|prc command containing an AXIS movement</item>
                <item name="InstanceGuid" type_name="gh_guid" type_code="9">bff3b2b5-5490-4edb-90a7-8692e0a46800</item>
                <item name="Name" type_name="gh_string" type_code="10">KUKA|prc Command</item>
                <item name="NickName" type_name="gh_string" type_code="10">COMMAND</item>
                <item name="Optional" type_name="gh_bool" type_code="1">false</item>
                <item name="SourceCount" type_name="gh_int32" type_code="3">0</item>
              </items>
              <chunks count="1">
                <chunk name="Attributes">
                  <items count="2">
                    <item name="Bounds" type_name="gh_drawing_rectanglef" type_code="35">
                      <X>28385</X>
                      <Y>4816</Y>
                      <W>68</W>
                      <H>140</H>
                    </item>
                    <item name="Pivot" type_name="gh_drawing_pointf" type_code="31">
                      <X>28419</X>
                      <Y>4886</Y>
                    </item>
                  </items>
                </chunk>
              </chunks>
            </chunk>
          </chunks>
        </chunk>
      </chunks>
    </chunk>
  </chunks>
</chunk>